bitable_mcp/__init__.py
bitable_mcp/cli.py
bitable_mcp/server.py
bitable_mcp-0.2.1.dist-info/METADATA
bitable_mcp-0.2.1.dist-info/WHEEL
bitable_mcp-0.2.1.dist-info/entry_points.txt
bitable_mcp-0.2.1.dist-info/RECORD
