Metadata-Version: 2.4
Name: bitable-mcp
Version: 0.2.1
Summary: This MCP server provides access to Lark bitable through the Model Context Protocol.
Requires-Python: >=3.10
Requires-Dist: mcp==1.3.0
Requires-Dist: pybitable
Requires-Dist: typer
